social_spam/__init__.py
social_spam/mail.py
social_spam/telegram.py
social_spam/vkontakte.py
social_spam/whatsapp.py
social_spam-1.3.0.dist-info/licenses/LICENSE.md
social_spam-1.3.0.dist-info/METADATA
social_spam-1.3.0.dist-info/WHEEL
social_spam-1.3.0.dist-info/top_level.txt
social_spam-1.3.0.dist-info/RECORD
