Metadata-Version: 2.4
Name: social-spam
Version: 1.3.0
Summary: Powerful Python package for messaging across multiple platforms (Telegram, VKontakte, WhatsApp, Email)
Author-email: neluckoff <neluckoff@gmail.com>
Maintainer-email: neluckoff <neluckoff@gmail.com>
License: MIT
Project-URL: Homepage, https://github.com/neluckoff/social_spam
Project-URL: Documentation, https://github.com/neluckoff/social_spam/tree/master/docs
Project-URL: Repository, https://github.com/neluckoff/social_spam
Project-URL: Download, https://github.com/neluckoff/social_spam/archive/master.zip
Project-URL: Changelog, https://github.com/neluckoff/social_spam/blob/master/CHANGELOG.md
Project-URL: Bug Tracker, https://github.com/neluckoff/social_spam/issues
Keywords: telegram,vkontakte,whatsapp,email,messaging,spam,bulk-send,mass-messaging,social-media,pyrogram,vk-api,pywhatkit,smtp
Classifier: Development Status :: 4 - Beta
Classifier: Intended Audience :: Developers
Classifier: Intended Audience :: End Users/Desktop
Classifier: License :: OSI Approved :: MIT License
Classifier: Operating System :: OS Independent
Classifier: Operating System :: POSIX
Classifier: Operating System :: MacOS :: MacOS X
Classifier: Operating System :: Microsoft :: Windows
Classifier: Programming Language :: Python
Classifier: Programming Language :: Python :: 3
Classifier: Programming Language :: Python :: 3.8
Classifier: Programming Language :: Python :: 3.9
Classifier: Programming Language :: Python :: 3.10
Classifier: Programming Language :: Python :: 3.11
Classifier: Programming Language :: Python :: 3.12
Classifier: Programming Language :: Python :: 3 :: Only
Classifier: Topic :: Communications
Classifier: Topic :: Communications :: Chat
Classifier: Topic :: Communications :: Email
Classifier: Topic :: Software Development :: Libraries :: Python Modules
Classifier: Topic :: Utilities
Requires-Python: >=3.8
License-File: LICENSE.md
Requires-Dist: alive-progress>=3.0.0
Requires-Dist: pyrogram>=2.0.0
Requires-Dist: vk-api>=11.9.0
Requires-Dist: pywhatkit>=5.0
Provides-Extra: telegram-speedup
Requires-Dist: TgCrypto>=1.2.0; extra == "telegram-speedup"
Provides-Extra: dev
Requires-Dist: pytest>=7.0.0; extra == "dev"
Requires-Dist: pytest-cov>=4.0.0; extra == "dev"
Requires-Dist: flake8>=6.0.0; extra == "dev"
Requires-Dist: black>=23.0.0; extra == "dev"
Requires-Dist: mypy>=1.0.0; extra == "dev"
Provides-Extra: all
Requires-Dist: TgCrypto>=1.2.0; extra == "all"
Dynamic: license-file
